setup.py
django_multiforloop.egg-info/PKG-INFO
django_multiforloop.egg-info/SOURCES.txt
django_multiforloop.egg-info/dependency_links.txt
django_multiforloop.egg-info/top_level.txt
multiforloop/__init__.py
multiforloop/models.py
multiforloop/tests.py
multiforloop/views.py
multiforloop/templatetags/__init__.py
multiforloop/templatetags/multifor.py