Metadata-Version: 2.1
Name: django-multiforloop
Version: 0.3.0
Summary: UNKNOWN
Home-page: http://github.org/gabrielgrant/django-multiforloop/
Author: Gabriel Grant
Author-email: g@briel.ca
License: LGPL
Platform: UNKNOWN
